nhdspy/__init__.py
nhdspy/helpers.py
nhdspy/NHDS/COPYING
nhdspy/NHDS/LICENSE
nhdspy/NHDS/Makefile
nhdspy/NHDS/README
nhdspy/NHDS/example_parameters.in
nhdspy/NHDS/kaw.in
nhdspy/NHDS/parameters_copy.in
nhdspy/NHDS/src/1modules.f90
nhdspy/NHDS/src/NHDS.f90
nhdspy/NHDS/src/calc_polarization.f90
nhdspy/NHDS/src/calc_xi.f90
nhdspy/NHDS/src/dispfunct.f90
nhdspy/NHDS/src/disptensor.f90
nhdspy/NHDS/src/newton_method.f90
nhdspy/NHDS/src/parameters.f90
nhdspy/NHDS/src/suscep.f90
nhdspy/NHDS/src/waveenergy.f90
nhdspy/NHDS/src/write_delta_f.f90.copy
nhdspy-0.1.dist-info/LICENSE
nhdspy-0.1.dist-info/METADATA
nhdspy-0.1.dist-info/WHEEL
nhdspy-0.1.dist-info/top_level.txt
nhdspy-0.1.dist-info/RECORD
