Metadata-Version: 2.1
Name: nhdspy
Version: 0.1
Summary: Python wrapper for the New Hampshire Dispersion Solver
Home-page: https://github.com/dstansby/nhdspy
Author: David Stansby
Author-email: dstansby@gmail.com
License: MIT
Platform: UNKNOWN
Classifier: Development Status :: 4 - Beta
Classifier: Environment :: Console
Classifier: Intended Audience :: Science/Research
Classifier: Natural Language :: English
Classifier: Programming Language :: Python :: 3
Classifier: Topic :: Scientific/Engineering :: Physics
Requires-Python: >=3.5
Requires-Dist: numpy
